quanty/__init__.py
quanty-0.0.1.dist-info/LICENSE
quanty-0.0.1.dist-info/METADATA
quanty-0.0.1.dist-info/WHEEL
quanty-0.0.1.dist-info/top_level.txt
quanty-0.0.1.dist-info/RECORD
