Metadata-Version: 2.1
Name: quanty
Version: 0.0.1
Summary: Python 量化交易框架!
Home-page: https://github.com/EVA-JianJun/quanty
Author: jianjun
Author-email: 910667956@qq.com
License-File: LICENSE
